CHANGES.rst
MANIFEST.in
README.rst
setup.py
tomcom/__init__.py
tomcom.plone.easyvoc.egg-info/PKG-INFO
tomcom.plone.easyvoc.egg-info/SOURCES.txt
tomcom.plone.easyvoc.egg-info/dependency_links.txt
tomcom.plone.easyvoc.egg-info/entry_points.txt
tomcom.plone.easyvoc.egg-info/namespace_packages.txt
tomcom.plone.easyvoc.egg-info/not-zip-safe
tomcom.plone.easyvoc.egg-info/requires.txt
tomcom.plone.easyvoc.egg-info/top_level.txt
tomcom/plone/__init__.py
tomcom/plone/easyvoc/__init__.py
tomcom/plone/easyvoc/browser.py
tomcom/plone/easyvoc/configure.zcml
tomcom/plone/easyvoc/profiles.zcml
tomcom/plone/easyvoc/locales/plone.pot
tomcom/plone/easyvoc/locales/de/LC_MESSAGES/plone.po
tomcom/plone/easyvoc/resource/img/dictionary.png
tomcom/plone/easyvoc/resource/js/easyvoc.js
tomcom/plone/easyvoc/templates/configure_easyvoc.pt
tomcom/plone/easyvoc/templates/js_easyvoc_edit.pt