Metadata-Version: 1.1
Name: tomcom.plone.easyvoc
Version: 4.3.0.3
Summary: A easy to use add on to define selectable values with numbered key.
Home-page: https://github.com/tomcom-de/tomcom.plone.easyvoc
Author: tomcom GmbH
Author-email: mailto:info@tomcom.de
License: GPL2
Keywords: tomcom plone
Platform: UNKNOWN
Classifier: Framework :: Plone
Classifier: Framework :: Plone :: 4.3
Classifier: Programming Language :: Python
Classifier: Topic :: Software Development :: Libraries :: Python Modules
